ciroh_plugins/__init__.py
ciroh_plugins/drought/__init__.py
ciroh_plugins/drought/drought_map.py
ciroh_plugins/drought/drought_pie.py
ciroh_plugins/drought/drought_plot.py
ciroh_plugins/drought/drought_table.py
ciroh_plugins/drought/sourceUrls.py
ciroh_plugins/drought/utilities.py
ciroh_plugins/nwmps/__init__.py
ciroh_plugins/nwmps/gauges.py
ciroh_plugins/nwmps/olmap.py
ciroh_plugins/nwmps/reaches.py
ciroh_plugins/nwmps/service.py
ciroh_plugins/nwmps/utilities.py
ciroh_plugins-0.0.2.dist-info/LICENSE
ciroh_plugins-0.0.2.dist-info/METADATA
ciroh_plugins-0.0.2.dist-info/WHEEL
ciroh_plugins-0.0.2.dist-info/entry_points.txt
ciroh_plugins-0.0.2.dist-info/top_level.txt
ciroh_plugins-0.0.2.dist-info/RECORD
